rhealsf/__init__.py
rhealsf/dggs_functions.py
rhealpix_sf-0.4.1.dist-info/LICENSE
rhealpix_sf-0.4.1.dist-info/WHEEL
rhealpix_sf-0.4.1.dist-info/METADATA
rhealpix_sf-0.4.1.dist-info/RECORD
